[
  1,
  [
    "54mYKZhPFLF42bKPrG2R/W"
  ],
  [
    "_textureSetter"
  ],
  [
    "cc.SpriteFrame"
  ],
  0,
  [
    [
      [
        {
          "name": "ic_backGame",
          "rect": [
            1321,
            1394,
            79,
            78
          ],
          "offset": [
            0,
            0
          ],
          "originalSize": [
            79,
            78
          ],
          "rotated": 1,
          "capInsets": [
            0,
            0,
            0,
            0
          ]
        }
      ],
      [
        0
      ],
      0,
      [
        0
      ],
      [
        0
      ],
      [
        0
      ]
    ],
    [
      [
        {
          "name": "ic_chu_ban",
          "rect": [
            1321,
            1570,
            38,
            33
          ],
          "offset": [
            0,
            0
          ],
          "originalSize": [
            38,
            33
          ],
          "rotated": 1,
          "capInsets": [
            0,
            0,
            0,
            0
          ]
        }
      ],
      [
        0
      ],
      0,
      [
        0
      ],
      [
        0
      ],
      [
        0
      ]
    ],
    [
      [
        {
          "name": "ic_dongho",
          "rect": [
            1329,
            1028,
            364,
            393
          ],
          "offset": [
            0,
            6
          ],
          "originalSize": [
            364,
            405
          ],
          "rotated": 1,
          "capInsets": [
            0,
            0,
            0,
            0
          ]
        }
      ],
      [
        0
      ],
      0,
      [
        0
      ],
      [
        0
      ],
      [
        0
      ]
    ]
  ]
]